LICENSE
MANIFEST.in
README.rst
requirements.txt
setup.cfg
setup.py
versioneer.py
rafem/FP.py
rafem/SLR.py
rafem/__init__.py
rafem/_version.py
rafem/avulse.py
rafem/avulsion_utils.py
rafem/diffuse.py
rafem/downcut.py
rafem/flux.py
rafem/main.py
rafem/prof.py
rafem/riverbmi.py
rafem/rivermodule.py
rafem/steep_desc.py
rafem/subside.py
rafem.egg-info/PKG-INFO
rafem.egg-info/SOURCES.txt
rafem.egg-info/dependency_links.txt
rafem.egg-info/entry_points.txt
rafem.egg-info/requires.txt
rafem.egg-info/top_level.txt