Metadata-Version: 1.1
Name: rafem
Version: 0.4.3
Summary: River Avulsion Flooplain Evolution Model
Home-page: https://github.com/katmratliff/avulsion-bmi
Author: Katherine Ratliff
Author-email: k.ratliff@duke.edu
License: MIT
Platform: UNKNOWN
Classifier: Intended Audience :: Science/Research
Classifier: License :: OSI Approved :: MIT License
Classifier: Operating System :: OS Independent
Classifier: Programming Language :: Python :: 3.6
Classifier: Programming Language :: Python :: 3.7
Classifier: Programming Language :: Python :: 3.8
Classifier: Topic :: Scientific/Engineering :: Physics
